[{"name":"Anh","seo":"anh","value":"v0"},{"name":"Canada","seo":"canada","value":"v1"},{"name":"Hàn Quốc","seo":"han-quoc","value":"v2"},{"name":"Hồng Kông","seo":"hong-kong","value":"v3"},{"name":"Mỹ","seo":"my","value":"v4"},{"name":"Nhật Bản","seo":"nhat-ban","value":"v5"},{"name":"Pháp","seo":"phap","value":"v6"},{"name":"Thái Lan","seo":"thai-lan","value":"v7"},{"name":"Trung Quốc","seo":"trung-quoc","value":"v8"},{"name":"Việt Nam","seo":"viet-nam","value":"v9"},{"name":"Úc","seo":"uc","value":"10"},{"name":"Đài Loan","seo":"dai-loan","value":"11"},{"name":"Ấn Độ","seo":"an-do","value":"12"},{"name":"Quốc gia khác","seo":"khac","value":"13"}]